tsia/__init__.py
tsia/diagnostics/__init__.py
tsia/diagnostics/histograms.py
tsia/diagnostics/profiling.py
tsia/markov/__init__.py
tsia/markov/mtf.py
tsia/network_graph/__init__.py
tsia/network_graph/ng.py
tsia/plot/__init__.py
tsia/plot/plot.py
tsia/utils/__init__.py
tsia/utils/tools.py
tsia-0.1.14.dist-info/METADATA
tsia-0.1.14.dist-info/WHEEL
tsia-0.1.14.dist-info/top_level.txt
tsia-0.1.14.dist-info/RECORD
