Metadata-Version: 2.2
Name: tsia
Version: 0.1.14
Summary: A Python package for time series analysis through images
Home-page: https://github.com/michaelhoarau/tsia
Download-URL: https://github.com/michaelhoarau/tsia
Maintainer: Michael Hoarau
Maintainer-email: michael.hoarau@gmail.com
License: MIT
Classifier: Development Status :: 3 - Alpha
Classifier: Intended Audience :: Science/Research
Classifier: Intended Audience :: Developers
Classifier: License :: OSI Approved :: MIT License
Classifier: Programming Language :: Python
Classifier: Topic :: Software Development
Classifier: Topic :: Scientific/Engineering
Classifier: Programming Language :: Python :: 3.7
Requires-Dist: networkx>=2.5
Requires-Dist: numpy>=1.17.5
Requires-Dist: numba>=0.48.0
Requires-Dist: python-louvain>=0.14.0
Requires-Dist: pyts>=0.11.0
Dynamic: classifier
Dynamic: description
Dynamic: description-content-type
Dynamic: download-url
Dynamic: home-page
Dynamic: license
Dynamic: maintainer
Dynamic: maintainer-email
Dynamic: requires-dist
Dynamic: summary
